qsolve/__init__.py
qsolve/units.py
qsolve/core/__init__.py
qsolve/core/qsolve_core.cp311-win_amd64.pyd
qsolve/core/qsolve_core.cpython-310-x86_64-linux-gnu.so
qsolve/core/qsolve_core.cpython-311-x86_64-linux-gnu.so
qsolve/figures/__init__.py
qsolve/figures/figures_1d/__init__.py
qsolve/figures/figures_1d/figure_eigenstates_lse_1d/__init__.py
qsolve/figures/figures_1d/figure_eigenstates_lse_1d/fig_control_inputs.py
qsolve/figures/figures_1d/figure_eigenstates_lse_1d/fig_psi_abs_squared_1d.py
qsolve/figures/figures_1d/figure_eigenstates_lse_1d/fig_psi_re_im_1d.py
qsolve/figures/figures_1d/figure_eigenstates_lse_1d/figure_eigenstates_lse_1d.py
qsolve/figures/figures_1d/figure_eigenstates_lse_1d/resources/__init__.py
qsolve/figures/figures_1d/figure_eigenstates_lse_1d/resources/fig_density.py
qsolve/figures/figures_1d/figure_eigenstates_lse_1d/resources/fig_density_x.py
qsolve/figures/figures_1d/figure_eigenstates_lse_1d/resources/fig_global_phase_difference.py
qsolve/figures/figures_1d/figure_eigenstates_lse_1d/resources/fig_imag_part.py
qsolve/figures/figures_1d/figure_eigenstates_lse_1d/resources/fig_number_imbalance.py
qsolve/figures/figures_1d/figure_eigenstates_lse_1d/resources/fig_phase.py
qsolve/figures/figures_1d/figure_eigenstates_lse_1d/resources/fig_phase_difference_xy.py
qsolve/figures/figures_1d/figure_eigenstates_lse_1d/resources/fig_phase_difference_xz.py
qsolve/figures/figures_1d/figure_eigenstates_lse_1d/resources/fig_phase_difference_z_x1_x2.py
qsolve/figures/figures_1d/figure_eigenstates_lse_1d/resources/fig_real_part.py
qsolve/figures/figures_1d/figure_eigenstates_lse_1d/resources/fig_real_part_x.py
qsolve/figures/figures_1d/figure_main_1d/__init__.py
qsolve/figures/figures_1d/figure_main_1d/fig_control_inputs.py
qsolve/figures/figures_1d/figure_main_1d/fig_psi_abs_squared_1d.py
qsolve/figures/figures_1d/figure_main_1d/fig_psi_re_im_1d.py
qsolve/figures/figures_1d/figure_main_1d/figure_main_1d.py
qsolve-0.3.2.dist-info/METADATA
qsolve-0.3.2.dist-info/WHEEL
qsolve-0.3.2.dist-info/top_level.txt
qsolve-0.3.2.dist-info/RECORD
