Metadata-Version: 2.1
Name: qsolve
Version: 0.3.2
Summary: Numerical framework for the simulation and optimization of ultracold atom experiments
Home-page: https://github.com/jfmennemann/qsolve
Author: Jan-Frederik Mennemann
Author-email: jfmennemann@gmx.de
